smv2/__init__.py
smv2/smv2.py
smv2-0.0.6.dist-info/LICENSE
smv2-0.0.6.dist-info/METADATA
smv2-0.0.6.dist-info/WHEEL
smv2-0.0.6.dist-info/entry_points.txt
smv2-0.0.6.dist-info/top_level.txt
smv2-0.0.6.dist-info/RECORD
