Metadata-Version: 2.1
Name: smv2
Version: 0.0.6
Summary: The CLI Tool for SM.MS, based on API v2.
Home-page: https://github.com/n0vad3v/smv2
Author: Nova Kwok
Author-email: noc@nova.moe
License: UNKNOWN
Platform: UNKNOWN
Classifier: Programming Language :: Python :: 3
Classifier: License :: OSI Approved :: GNU General Public License v3 (GPLv3)
Classifier: Operating System :: OS Independent
Requires-Dist: requests
Requires-Dist: terminaltables
